europarser/__about__.py
europarser/__init__.py
europarser/daniel_light.py
europarser/endpoint.py
europarser/lang_detect.py
europarser/main.py
europarser/models.py
europarser/pipeline.py
europarser/pivot.py
europarser/pivots_from_files.py
europarser/utils.py
europarser/api/__init__.py
europarser/api/api.py
europarser/api/utils.py
europarser/api/static/basic.min.css
europarser/api/static/convertir.svg
europarser/api/static/convertir_blanc.svg
europarser/api/static/dropzone_handler.js
europarser/api/static/dwk.png
europarser/api/static/favicon.ico
europarser/api/static/index.js
europarser/api/static/logo.svg
europarser/api/static/logo_ceres.png
europarser/api/static/pedro.mp3
europarser/api/static/pedro.png
europarser/api/static/popover.js
europarser/api/static/style.css
europarser/api/static/support_100.png
europarser/api/static/support_50.png
europarser/api/templates/index.html
europarser/transformers/__init__.py
europarser/transformers/to_csv.py
europarser/transformers/to_excel.py
europarser/transformers/to_gephi.py
europarser/transformers/to_iramuteq.py
europarser/transformers/to_json.py
europarser/transformers/to_markdown.py
europarser/transformers/to_stats.py
europarser/transformers/to_txm.py
europarser/transformers/transformer.py
europarser-0.3.5.dist-info/METADATA
europarser-0.3.5.dist-info/WHEEL
europarser-0.3.5.dist-info/entry_points.txt
europarser-0.3.5.dist-info/licenses/LICENSE.txt
europarser-0.3.5.dist-info/RECORD
