Metadata-Version: 2.4
Name: europarser
Version: 0.3.5
Project-URL: Documentation, https://github.com/CERES-sorbonne/europarser#readme
Project-URL: Issues, https://github.com/CERES-sorbonne/europarser/issues
Project-URL: Source, https://github.com/CERES-sorbonne/europarser
Author-email: Marceau <pypi@marceau-h.fr>
License-Expression: AGPL-3.0-or-later
License-File: LICENSE.txt
Classifier: Development Status :: 5 - Production/Stable
Classifier: Programming Language :: Python
Classifier: Programming Language :: Python :: 3.9
Classifier: Programming Language :: Python :: 3.10
Classifier: Programming Language :: Python :: 3.11
Classifier: Programming Language :: Python :: 3.12
Classifier: Programming Language :: Python :: 3.13
Classifier: Programming Language :: Python :: Implementation :: CPython
Classifier: Programming Language :: Python :: Implementation :: PyPy
Requires-Python: >=3.9
Requires-Dist: aiofiles
Requires-Dist: beautifulsoup4
Requires-Dist: cython
Requires-Dist: fastapi
Requires-Dist: faust-cchardet
Requires-Dist: filedetect
Requires-Dist: jinja2
Requires-Dist: langid
Requires-Dist: lxml
Requires-Dist: matplotlib
Requires-Dist: numpy
Requires-Dist: pandas
Requires-Dist: plotly
Requires-Dist: polars
Requires-Dist: py3langid
Requires-Dist: pyarrow
Requires-Dist: pydantic
Requires-Dist: python-dateutil
Requires-Dist: python-multipart
Requires-Dist: tqdm
Requires-Dist: uvicorn[standard]
Requires-Dist: xlsxwriter
